Metadata-Version: 2.4
Name: adafruit-circuitpython-pixel-framebuf
Version: 1.1.18
Summary: Neopixel and Dotstar Framebuffer Helper
Author-email: Adafruit Industries <circuitpython@adafruit.com>
License: MIT
Project-URL: Homepage, https://github.com/adafruit/Adafruit_CircuitPython_Pixel_Framebuf
Keywords: adafruit,blinka,circuitpython,micropython,pixel_framebuf,neopixel,framebuf,framebuffer,dotstar,matrix,animation,led,ws2812,ap102
Classifier: Intended Audience :: Developers
Classifier: Topic :: Software Development :: Libraries
Classifier: Topic :: Software Development :: Embedded Systems
Classifier: Topic :: System :: Hardware
Classifier: License :: OSI Approved :: MIT License
Classifier: Programming Language :: Python :: 3
License-File: LICENSE
Requires-Dist: Adafruit-Blinka
Requires-Dist: adafruit-circuitpython-framebuf>=1.4.2
Requires-Dist: adafruit-circuitpython-led-animation
Requires-Dist: adafruit-circuitpython-typing~=1.4
Provides-Extra: optional
Dynamic: license-file
